simple_sql_abs/__init__.py
simple_sql_abs/dao.py
simple_sql_abs/singleton.py
simple_sql_abstraction-1.0.0.dist-info/LICENCE.txt
simple_sql_abstraction-1.0.0.dist-info/METADATA
simple_sql_abstraction-1.0.0.dist-info/WHEEL
simple_sql_abstraction-1.0.0.dist-info/top_level.txt
simple_sql_abstraction-1.0.0.dist-info/RECORD
