Metadata-Version: 2.1
Name: simple-sql-abstraction
Version: 1.0.0
Summary: Simple SQL abstraction
Home-page: https://github.com/prbpedro/simple_sql_abstraction
Author: Pedro Ribeiro Baptista
Author-email: prbpedro@gmail.com
License: UNKNOWN
Platform: UNKNOWN
Classifier: Programming Language :: Python :: 3
Classifier: License :: OSI Approved :: MIT License
Classifier: Operating System :: OS Independent
